secure_smtplib-0.1.1.dist-info/metadata.json
secure_smtplib-0.1.1.dist-info/zip-safe
secure_smtplib-0.1.1.dist-info/WHEEL
secure_smtplib-0.1.1.dist-info/top_level.txt
secure_smtplib-0.1.1.dist-info/METADATA
secure_smtplib-0.1.1.dist-info/DESCRIPTION.rst
secure_smtplib-0.1.1.dist-info/RECORD
secure_smtplib/__init__.py
