Metadata-Version: 1.0
Name: secure-smtplib
Version: 0.1.1
Summary: Secure SMTP subclasses for Python 2
Home-page: https://github.com/graingert/secure-smtplib
Author: Thomas Grainger
Author-email: secure-smtplib@graingert.co.uk
License: UNKNOWN
Keywords: smtplib,TLS,SSL,verify,validate,ca_cert,ca
Platform: UNKNOWN
